attachments/__init__.py
attachments/admin.py
attachments/apps.py
attachments/fields.py
attachments/forms.py
attachments/models.py
attachments/receivers.py
attachments/serializers.py
attachments/tests.py
attachments/urls.py
attachments/views.py
attachments/widgets.py
attachments/components/attachments.stories.js
attachments/components/cookies.js
attachments/components/delete_button.js
attachments/components/image_box.js
attachments/components/image_grid.js
attachments/components/image_info.js
attachments/components/image_picker.js
attachments/components/multiple_image.js
attachments/components/picker_box.js
attachments/components/search_bar.js
attachments/components/sortable_grid.js
attachments/components/tags_bar.js
attachments/components/upload_box.js
attachments/locale/zh_Hans/LC_MESSAGES/django.mo
attachments/locale/zh_Hans/LC_MESSAGES/django.po
attachments/migrations/0001_initial.py
attachments/migrations/__init__.py
attachments/static/attachments/image_picker.js
attachments/static/attachments/image_picker.js.map
attachments/static/attachments/multiple_image.js
attachments/static/attachments/multiple_image.js.map
attachments/static/attachments/widgets/richtext.js
attachments/static/attachments/widgets/zh_CN.js
attachments/templates/attachments/widgets/image_picker.html
attachments/templates/attachments/widgets/multiple_image.html
django_simple_attachments-0.2.3.dist-info/LICENSE
django_simple_attachments-0.2.3.dist-info/METADATA
django_simple_attachments-0.2.3.dist-info/WHEEL
django_simple_attachments-0.2.3.dist-info/top_level.txt
django_simple_attachments-0.2.3.dist-info/RECORD
