Metadata-Version: 2.1
Name: django-simple-attachments
Version: 0.2.3
Summary: Django Simple Attachment Model.
Home-page: https://github.com/ChanMo/django-simple-attachments.git
Author: ChanMo
Author-email: chan.mo@outlook.com
License: MIT License
Keywords: django,attachment,image,storage,postgres
Platform: UNKNOWN
Classifier: Environment :: Web Environment
Classifier: Framework :: Django
Classifier: Framework :: Django :: 3.0
Classifier: Intended Audience :: Developers
Classifier: License :: OSI Approved :: MIT License
Classifier: Operating System :: OS Independent
Classifier: Programming Language :: Python
Classifier: Programming Language :: Python :: 3
Classifier: Programming Language :: Python :: 3 :: Only
Classifier: Programming Language :: Python :: 3.6
Classifier: Programming Language :: Python :: 3.7
Classifier: Programming Language :: Python :: 3.8
Classifier: Topic :: Internet :: WWW/HTTP
Classifier: Topic :: Internet :: WWW/HTTP :: Dynamic Content
